{
	"info": {
		"_postman_id": "3f7a5e5b-cd50-4e60-b83d-20dd57f3f20b",
		"name": "SteelTrace",
		"schema": "https://schema.getpostman.com/json/collection/v2.1.0/collection.json"
	},
	"item": [
		{
			"name": "Tests",
			"item": [
				{
					"name": "Chemical Composition",
					"item": [
						{
							"name": "Create",
							"request": {
								"method": "POST",
								"header": [
									{
										"key": "Content-Type",
										"name": "Content-Type",
										"value": "application/json",
										"type": "text"
									}
								],
								"body": {
									"mode": "raw",
									"raw": "{\n  \"item_heat\": 12341,\n  \"signed\": false,\n  \"elements\": [],\n  \"grade\": \"S31254\",\n  \"norm\": \"A240/A240M-18\",\n  \"en_number\": 123,\n  \"product_name\": \"name\",\n  \"events\": [{\n\t  \"value\": \"C\",\n\t  \"min\": 0,\n\t  \"max\": 0.020,\n\t  \"bm\": 0\n   }]\n}"
								},
								"url": {
									"raw": "http://localhost:5000/tests/chemical-compositions",
									"protocol": "http",
									"host": [
										"localhost"
									],
									"port": "5000",
									"path": [
										"tests",
										"chemical-compositions"
									]
								}
							},
							"response": []
						},
						{
							"name": "Update",
							"request": {
								"method": "PUT",
								"header": [
									{
										"key": "Content-Type",
										"name": "Content-Type",
										"value": "application/json",
										"type": "text"
									}
								],
								"body": {
									"mode": "raw",
									"raw": "{\n  \"item_heat\": 12341,\n  \"signed\": false,\n  \"elements\": [\n            {\n                \"_id\": \"5cb659d759f2e220b6520be0\",\n                \"min\": 0,\n                \"max\": 0.02,\n                \"bm\": 0,\n                \"element\": \"C\"\n            },\n            {\n                \"_id\": \"5cb659d759f2e220b6520bdf\",\n                \"min\": 0,\n                \"max\": 1,\n                \"bm\": \"0\"\n            },\n            {\n                \"_id\": \"5cb659d759f2e220b6520bde\",\n                \"min\": 0,\n                \"max\": 0.03,\n                \"bm\": \"0\"\n            },\n            {\n                \"_id\": \"5cb659d759f2e220b6520bdd\",\n                \"min\": 0,\n                \"max\": 0.01,\n                \"bm\": \"0\"\n            },\n            {\n                \"_id\": \"5cb659d759f2e220b6520bdc\",\n                \"min\": 0,\n                \"max\": 0.8,\n                \"bm\": \"0\"\n            },\n            {\n                \"_id\": \"5cb659d759f2e220b6520bdb\",\n                \"min\": 19.5,\n                \"max\": 20.5,\n                \"bm\": \"0\"\n            },\n            {\n                \"_id\": \"5cb659d759f2e220b6520bda\",\n                \"min\": 17.5,\n                \"max\": 18.5,\n                \"bm\": \"0\"\n            },\n            {\n                \"_id\": \"5cb659d759f2e220b6520bd9\",\n                \"min\": 6,\n                \"max\": 0.5,\n                \"bm\": \"0\"\n            },\n            {\n                \"_id\": \"5cb659d759f2e220b6520bd8\",\n                \"min\": 0.18,\n                \"max\": 0.25,\n                \"bm\": \"0\"\n            },\n            {\n                \"_id\": \"5cb659d759f2e220b6520bd7\",\n                \"min\": 0.5,\n                \"max\": 1,\n                \"bm\": \"0\"\n            },\n            {\n                \"_id\": \"5cb659d759f2e220b6520bd6\",\n                \"min\": 0,\n                \"max\": 0,\n                \"bm\": \"0\"\n            }\n        ],\n  \"grade\": \"S31254\",\n  \"norm\": \"A240/A240M-18\",\n  \"en_number\": 123,\n  \"product_name\": \"name\",\n  \"events\": [{\n\t  \"value\": \"C\",\n\t  \"min\": 0,\n\t  \"max\": 0.020,\n\t  \"bm\": 0\n   }]\n}"
								},
								"url": {
									"raw": "http://localhost:5000/tests/chemical-compositions/5cb475db8b717f50ce39c974",
									"protocol": "http",
									"host": [
										"localhost"
									],
									"port": "5000",
									"path": [
										"tests",
										"chemical-compositions",
										"5cb475db8b717f50ce39c974"
									]
								}
							},
							"response": []
						},
						{
							"name": "Single",
							"request": {
								"method": "GET",
								"header": [],
								"url": {
									"raw": "http://localhost:5000/tests/chemical-compositions/5cbdc7edab155e54ca8c9326",
									"protocol": "http",
									"host": [
										"localhost"
									],
									"port": "5000",
									"path": [
										"tests",
										"chemical-compositions",
										"5cbdc7edab155e54ca8c9326"
									]
								}
							},
							"response": []
						}
					],
					"_postman_isSubFolder": true
				},
				{
					"name": "Hardness Test",
					"item": [
						{
							"name": "Update",
							"request": {
								"method": "PUT",
								"header": [
									{
										"key": "Content-Type",
										"name": "Content-Type",
										"type": "text",
										"value": "application/json"
									}
								],
								"body": {
									"mode": "raw",
									"raw": " {\"elements\": [],\n  \"acceptance\": \"FG21D\",\n  \"norm\": \"23Fdw\"\n }"
								},
								"url": {
									"raw": "http://localhost:5000/tests/hardness-test/5cd015c902fcdd65a88a9605",
									"protocol": "http",
									"host": [
										"localhost"
									],
									"port": "5000",
									"path": [
										"tests",
										"hardness-test",
										"5cd015c902fcdd65a88a9605"
									]
								}
							},
							"response": []
						},
						{
							"name": "Single",
							"request": {
								"method": "GET",
								"header": [],
								"url": {
									"raw": "http://localhost:5000/tests/hardness-test/5cd015c902fcdd65a88a9605",
									"protocol": "http",
									"host": [
										"localhost"
									],
									"port": "5000",
									"path": [
										"tests",
										"hardness-test",
										"5cd015c902fcdd65a88a9605"
									]
								}
							},
							"response": []
						}
					],
					"_postman_isSubFolder": true
				},
				{
					"name": "Bend Test",
					"item": [
						{
							"name": "Update",
							"request": {
								"method": "PUT",
								"header": [
									{
										"key": "Content-Type",
										"name": "Content-Type",
										"type": "text",
										"value": "application/json"
									}
								],
								"body": {
									"mode": "raw",
									"raw": " {\n \t\"testStandard\": \"awd\",\n      \"relatedStandard\": \"wdw\",\n      \"position\": \"awdwad\",\n      \"width\": 1,\n      \"height\": 2,\n      \"jig\": 5,\n      \"rollsDistance\": 1,\n      \"angle\": 234,\n      \"result\": \"Yes\",\n      \"notes\": \"Notes\"\n }"
								},
								"url": {
									"raw": "http://localhost:5000/tests/bend-test/5cd121cde4b6ab308fda7302",
									"protocol": "http",
									"host": [
										"localhost"
									],
									"port": "5000",
									"path": [
										"tests",
										"bend-test",
										"5cd121cde4b6ab308fda7302"
									]
								}
							},
							"response": []
						},
						{
							"name": "Single",
							"request": {
								"method": "GET",
								"header": [],
								"url": {
									"raw": "http://localhost:5000/tests/bend-test/5cc9f49754e60a23a73a4b3c",
									"protocol": "http",
									"host": [
										"localhost"
									],
									"port": "5000",
									"path": [
										"tests",
										"bend-test",
										"5cc9f49754e60a23a73a4b3c"
									]
								}
							},
							"response": []
						}
					],
					"_postman_isSubFolder": true
				},
				{
					"name": "Hydrostatic Test",
					"item": [
						{
							"name": "Update",
							"request": {
								"method": "PUT",
								"header": [
									{
										"key": "Content-Type",
										"name": "Content-Type",
										"value": "application/json",
										"type": "text"
									}
								],
								"body": {
									"mode": "raw",
									"raw": "{\n   \"material\":\"FD1\",\n \"testingFluid\": \"String\",\n  \"minTime\": \"String\",\n  \"diameter\": 1,\n \"weight\": 2,\n  \"size\": 4,\n  \"pressure\": \"String\",\n  \"result\": \"String\"\n}"
								},
								"url": {
									"raw": "http://localhost:5000/tests/hydrostatic-test/5cd03ef637b7d701af59",
									"protocol": "http",
									"host": [
										"localhost"
									],
									"port": "5000",
									"path": [
										"tests",
										"hydrostatic-test",
										"5cd03ef637b7d701af59"
									]
								}
							},
							"response": []
						},
						{
							"name": "Create",
							"request": {
								"method": "POST",
								"header": [
									{
										"key": "Content-Type",
										"name": "Content-Type",
										"type": "text",
										"value": "application/json"
									}
								],
								"body": {
									"mode": "raw",
									"raw": "{\n   \"material\":\"FG2\",\n \"testingFluid\": \"String\",\n  \"minTime\": 2,\n  \"diameter\": 1,\n \"weight\": 2,\n  \"size\": 4,\n  \"pressure\": \"String\",\n  \"result\": \"String\"\n}"
								},
								"url": {
									"raw": "http://localhost:5000/tests/hydrostatic-test",
									"protocol": "http",
									"host": [
										"localhost"
									],
									"port": "5000",
									"path": [
										"tests",
										"hydrostatic-test"
									]
								}
							},
							"response": []
						},
						{
							"name": "Single",
							"request": {
								"method": "GET",
								"header": [],
								"url": {
									"raw": "http://localhost:5000/tests/hydrostatic-test/5cd03ef637b7d701af593629",
									"protocol": "http",
									"host": [
										"localhost"
									],
									"port": "5000",
									"path": [
										"tests",
										"hydrostatic-test",
										"5cd03ef637b7d701af593629"
									]
								}
							},
							"response": []
						}
					],
					"_postman_isSubFolder": true
				},
				{
					"name": "Radio Graphic Report",
					"item": [
						{
							"name": "Update",
							"request": {
								"method": "PUT",
								"header": [
									{
										"key": "Content-Type",
										"name": "Content-Type",
										"value": "application/json",
										"type": "text"
									}
								],
								"body": {
									"mode": "raw",
									"raw": "{\n   \"workStage\": \"joi.string()\",\n  \"norm\": \"joi.string()\",\n  \"acceptance\": \"joi.string()\",\n  \"radioscopic\": \"joi.string()\",\n  \"source\": \"joi.string()\",\n  \"screen\": \"joi.string()\",\n  \"thicknessSourceSide\": 1,\n  \"thicknessFilmSide\": 1,\n  \"sourceDistance\": 2,\n  \"position\": \"joi.string()\",\n  \"density\": \"joi.string()\",\n  \"sourceSize\": 2,\n  \"iqiType\": \"joi.string()\",\n  \"filmType\": \"joi.string()\",\n  \"xRayApparatus\": \"joi.string()\",\n  \"tps\": \"joi.string()\",\n  \"kv\": 2,\n  \"ma\": \"joi.string()\",\n  \"expTime\": 5\n}"
								},
								"url": {
									"raw": "http://localhost:5000/tests/radio-graphic-report/5cd054bc27fd7b050fef3c0e",
									"protocol": "http",
									"host": [
										"localhost"
									],
									"port": "5000",
									"path": [
										"tests",
										"radio-graphic-report",
										"5cd054bc27fd7b050fef3c0e"
									]
								}
							},
							"response": []
						},
						{
							"name": "Single",
							"request": {
								"method": "GET",
								"header": [],
								"url": {
									"raw": "http://localhost:5000/tests/radio-graphic-report/5cd054bc27fd7b050fef3c0e",
									"protocol": "http",
									"host": [
										"localhost"
									],
									"port": "5000",
									"path": [
										"tests",
										"radio-graphic-report",
										"5cd054bc27fd7b050fef3c0e"
									]
								}
							},
							"response": []
						}
					],
					"_postman_isSubFolder": true
				},
				{
					"name": "Liquid Penatrant Test",
					"item": [
						{
							"name": "Update",
							"request": {
								"method": "PUT",
								"header": [
									{
										"key": "Content-Type",
										"name": "Content-Type",
										"value": "application/json",
										"type": "text"
									}
								],
								"body": {
									"mode": "raw",
									"raw": "{\n  \"norm\": \"joi.object()\",\n  \"acceptance\": \"joi.object()\",\n  \"workStage\": \"joi.string()\",\n  \"surfaceCondition\": \"joi.string()\",\n  \"method\": \"joi.object()\",\n  \"cleaner\": \"joi.string()\",\n  \"penetrant\": \"joi.string()\",\n  \"dev\": \"joi.string()\",\n  \"tradeName\": \"joi.string()\",\n  \"cleanedBy\": \"joi.string()\",\n  \"temperatureSurface\": 1,\n  \"ambientLevel\": 2,\n  \"penetrantApp\": \"joi.string()\",\n  \"dwelTime\": 3,\n  \"removalBy\": \"joi.string()\",\n  \"devApp\": \"dw\",\n \"devTime\": 1,\n  \"interpretationTime\": 5,\n  \"sketch\": \"joi.object()\",\n  \"result\": \"Acceptable\"\n}"
								},
								"url": {
									"raw": "http://localhost:5000/tests/liquid-penetrant-test/5cd15d1ff819d8697796a416",
									"protocol": "http",
									"host": [
										"localhost"
									],
									"port": "5000",
									"path": [
										"tests",
										"liquid-penetrant-test",
										"5cd15d1ff819d8697796a416"
									]
								}
							},
							"response": []
						},
						{
							"name": "Single",
							"request": {
								"method": "GET",
								"header": [],
								"url": {
									"raw": "http://localhost:5000/tests/liquid-penetrant-test/5cd09488e74fb838477a5e1b",
									"protocol": "http",
									"host": [
										"localhost"
									],
									"port": "5000",
									"path": [
										"tests",
										"liquid-penetrant-test",
										"5cd09488e74fb838477a5e1b"
									]
								}
							},
							"response": []
						},
						{
							"name": "Create Copy",
							"request": {
								"method": "POST",
								"header": [
									{
										"key": "Content-Type",
										"name": "Content-Type",
										"type": "text",
										"value": "application/json"
									}
								],
								"body": {
									"mode": "raw",
									"raw": "{\n  \"item_heat\": 12341,\n  \"signed\": false,\n  \"elements\": [],\n  \"grade\": \"S31254\",\n  \"norm\": \"A240/A240M-18\",\n  \"en_number\": 123,\n  \"product_name\": \"name\",\n  \"events\": [{\n\t  \"value\": \"C\",\n\t  \"min\": 0,\n\t  \"max\": 0.020,\n\t  \"bm\": 0\n   }]\n}"
								},
								"url": {
									"raw": "http://localhost:5000/tests/liquid-penetrant-test/",
									"protocol": "http",
									"host": [
										"localhost"
									],
									"port": "5000",
									"path": [
										"tests",
										"liquid-penetrant-test",
										""
									]
								}
							},
							"response": []
						}
					],
					"event": [
						{
							"listen": "prerequest",
							"script": {
								"id": "c3a109d8-30e7-4c7b-84d4-0f7f552407eb",
								"type": "text/javascript",
								"exec": [
									""
								]
							}
						},
						{
							"listen": "test",
							"script": {
								"id": "683e0783-177c-47f4-a4cd-de7b9e7fdc4e",
								"type": "text/javascript",
								"exec": [
									""
								]
							}
						}
					],
					"_postman_isSubFolder": true
				},
				{
					"name": "Single",
					"request": {
						"method": "GET",
						"header": [
							{
								"key": "X-Token-Jwt",
								"value": " eyJhbGciOiJIUzI1NiIsInR5cCI6IkpXVCJ9.eyJpZCI6IjVlMmVkNDc3ZDlhOTQwNDkzNjU3NTZhNCIsImZpcnN0bmFtZSI6ImR3dyIsImxhc3RuYW1lIjoiYXdkIiwicm9sZSI6IkFETUlOIiwiY29tcGFueSI6IjVlMmVkNDc3ZDlhOTQwNDkzNjU3NTZhNSIsImlhdCI6MTU4MjcxOTMwMywiZXhwIjoxNTgzNDE5MzAzfQ.j3jfvVAq-znhwvnVOJ-u7PLgkAT9NO9abrJcZ8COPtM",
								"type": "text"
							}
						],
						"url": {
							"raw": "http://localhost:5000/tests/1",
							"protocol": "http",
							"host": [
								"localhost"
							],
							"port": "5000",
							"path": [
								"tests",
								"1"
							]
						}
					},
					"response": []
				},
				{
					"name": "Remove",
					"request": {
						"method": "DELETE",
						"header": [
							{
								"key": "X-Token-Jwt",
								"value": "eyJhbGciOiJIUzI1NiIsInR5cCI6IkpXVCJ9.eyJpZCI6IjVlMmVkNDc3ZDlhOTQwNDkzNjU3NTZhNCIsImZpcnN0bmFtZSI6ImR3dyIsImxhc3RuYW1lIjoiYXdkIiwicm9sZSI6IkFETUlOIiwiY29tcGFueSI6IjVlMmVkNDc3ZDlhOTQwNDkzNjU3NTZhNSIsImlhdCI6MTU4MjcxOTMwMywiZXhwIjoxNTgzNDE5MzAzfQ.j3jfvVAq-znhwvnVOJ-u7PLgkAT9NO9abrJcZ8COPtM",
								"type": "text"
							}
						],
						"url": {
							"raw": "http://localhost:5000/tests/5e4d09f445aeb65eefa416a4",
							"protocol": "http",
							"host": [
								"localhost"
							],
							"port": "5000",
							"path": [
								"tests",
								"5e4d09f445aeb65eefa416a4"
							]
						}
					},
					"response": []
				},
				{
					"name": "List",
					"request": {
						"method": "GET",
						"header": [
							{
								"key": "X-Token-Jwt",
								"value": " eyJhbGciOiJIUzI1NiIsInR5cCI6IkpXVCJ9.eyJpZCI6IjVlMmVkNDc3ZDlhOTQwNDkzNjU3NTZhNCIsImZpcnN0bmFtZSI6ImR3dyIsImxhc3RuYW1lIjoiYXdkIiwicm9sZSI6IkFETUlOIiwiY29tcGFueSI6IjVlMmVkNDc3ZDlhOTQwNDkzNjU3NTZhNSIsImlhdCI6MTU4MjcxOTMwMywiZXhwIjoxNTgzNDE5MzAzfQ.j3jfvVAq-znhwvnVOJ-u7PLgkAT9NO9abrJcZ8COPtM",
								"type": "text"
							}
						],
						"url": {
							"raw": "http://localhost:5000/tests",
							"protocol": "http",
							"host": [
								"localhost"
							],
							"port": "5000",
							"path": [
								"tests"
							]
						}
					},
					"response": []
				},
				{
					"name": "Create",
					"request": {
						"method": "POST",
						"header": [
							{
								"key": "Content-Type",
								"name": "Content-Type",
								"value": "application/json",
								"type": "text"
							},
							{
								"key": "X-Token-Jwt",
								"value": "eyJhbGciOiJIUzI1NiIsInR5cCI6IkpXVCJ9.eyJpZCI6IjVlMmVkNDc3ZDlhOTQwNDkzNjU3NTZhNCIsImZpcnN0bmFtZSI6ImR3dyIsImxhc3RuYW1lIjoiYXdkIiwicm9sZSI6IkFETUlOIiwiY29tcGFueSI6IjVlMmVkNDc3ZDlhOTQwNDkzNjU3NTZhNSIsImlhdCI6MTU4MjcxOTMwMywiZXhwIjoxNTgzNDE5MzAzfQ.j3jfvVAq-znhwvnVOJ-u7PLgkAT9NO9abrJcZ8COPtM",
								"type": "text"
							}
						],
						"body": {
							"mode": "raw",
							"raw": "[{\n\t\"status\": \"FILLED\",\n\t\"type\": \"test_notes\"\n}]",
							"options": {
								"raw": {}
							}
						},
						"url": {
							"raw": "http://localhost:5000/tests",
							"protocol": "http",
							"host": [
								"localhost"
							],
							"port": "5000",
							"path": [
								"tests"
							]
						}
					},
					"response": []
				},
				{
					"name": "Update",
					"request": {
						"method": "PUT",
						"header": [
							{
								"key": "X-Token-Jwt",
								"value": " eyJhbGciOiJIUzI1NiIsInR5cCI6IkpXVCJ9.eyJpZCI6IjVlMmVkNDc3ZDlhOTQwNDkzNjU3NTZhNCIsImZpcnN0bmFtZSI6ImR3dyIsImxhc3RuYW1lIjoiYXdkIiwicm9sZSI6IkFETUlOIiwiY29tcGFueSI6IjVlMmVkNDc3ZDlhOTQwNDkzNjU3NTZhNSIsImlhdCI6MTU4MjcxOTMwMywiZXhwIjoxNTgzNDE5MzAzfQ.j3jfvVAq-znhwvnVOJ-u7PLgkAT9NO9abrJcZ8COPtM",
								"type": "text"
							},
							{
								"key": "Content-Type",
								"name": "Content-Type",
								"value": "application/json",
								"type": "text"
							}
						],
						"body": {
							"mode": "raw",
							"raw": "{\n\t\"type\": \"hydrostatic_test\",\n\t\"properties\": {\n\t\t\"material\":\"FG2\",\n\t\t\"testingFluid\": \"String\",\n\t\t\"minTime\": 2,\n\t\t\"diameter\": 1,\n\t\t\"weight\": 2,\n\t\t\"size\": 4,\n\t\t\"pressure\": \"String\",\n\t\t\"result\": \"String\"\n\t},\n\t\n\t\"witnesses\" : [{\n\t\t\"company\": \"123412\"}\n\t\t]\n}",
							"options": {
								"raw": {
									"language": "json"
								}
							}
						},
						"url": {
							"raw": "http://localhost:5000/tests/5e5d33be9a8e072a793a2764",
							"protocol": "http",
							"host": [
								"localhost"
							],
							"port": "5000",
							"path": [
								"tests",
								"5e5d33be9a8e072a793a2764"
							]
						}
					},
					"response": []
				},
				{
					"name": "Bulk",
					"request": {
						"method": "PUT",
						"header": [
							{
								"key": "X-Token-Jwt",
								"type": "text",
								"value": " eyJhbGciOiJIUzI1NiIsInR5cCI6IkpXVCJ9.eyJpZCI6IjVlMmVkNDc3ZDlhOTQwNDkzNjU3NTZhNCIsImZpcnN0bmFtZSI6ImR3dyIsImxhc3RuYW1lIjoiYXdkIiwicm9sZSI6IkFETUlOIiwiY29tcGFueSI6IjVlMmVkNDc3ZDlhOTQwNDkzNjU3NTZhNSIsImlhdCI6MTU4MjcxOTMwMywiZXhwIjoxNTgzNDE5MzAzfQ.j3jfvVAq-znhwvnVOJ-u7PLgkAT9NO9abrJcZ8COPtM"
							},
							{
								"key": "Content-Type",
								"name": "Content-Type",
								"type": "text",
								"value": "application/json"
							}
						],
						"body": {
							"mode": "raw",
							"raw": "[{}]",
							"options": {
								"raw": {
									"language": "json"
								}
							}
						},
						"url": {
							"raw": "http://localhost:5000/tests/bulk",
							"protocol": "http",
							"host": [
								"localhost"
							],
							"port": "5000",
							"path": [
								"tests",
								"bulk"
							]
						}
					},
					"response": []
				},
				{
					"name": "Sign",
					"request": {
						"method": "POST",
						"header": [
							{
								"key": "Content-Type",
								"name": "Content-Type",
								"type": "text",
								"value": "application/json"
							}
						],
						"body": {
							"mode": "raw",
							"raw": "{\n  \"signature\": \"1f345knb2bdk34a5d32\",\n  \"creator\": \"5c7e3bced3aef23d90990912\",\n  \"signer\": \"5c7e3bcdd3aef23d90990910\"\n}"
						},
						"url": {
							"raw": "http://localhost:5000/tests/5cd1e66aeb45082b9cdda187/sign",
							"protocol": "http",
							"host": [
								"localhost"
							],
							"port": "5000",
							"path": [
								"tests",
								"5cd1e66aeb45082b9cdda187",
								"sign"
							]
						}
					},
					"response": []
				}
			]
		},
		{
			"name": "Certificates",
			"item": [
				{
					"name": "Create",
					"request": {
						"method": "POST",
						"header": [
							{
								"key": "Content-Type",
								"name": "Content-Type",
								"value": "application/json",
								"type": "text"
							}
						],
						"body": {
							"mode": "raw",
							"raw": "{\n\"heat\": 1.52536,\n\"type\": 3.1,\n\"tests\": [],\n\"material_grade\": 1.45637,\n \"properties\": {\n\t\"product_type\": \"Pipe\",\n\t\"length\": 11.273,\n\t\"weight\": 432.34,\n\t\"outerDiameter\": 273.1,\n\t\"thickness\": 6.3,\n\t\"batchLength\": 60.000,\n\t\"currentForm\": true\n },\n \"norm\": \"ASTM A23\",\n \"tp_UNS\": \"S32432\"\n}"
						},
						"url": {
							"raw": "http://localhost:5000/certificates",
							"protocol": "http",
							"host": [
								"localhost"
							],
							"port": "5000",
							"path": [
								"certificates"
							]
						}
					},
					"response": []
				},
				{
					"name": "Split",
					"request": {
						"method": "POST",
						"header": [
							{
								"key": "Content-Type",
								"name": "Content-Type",
								"value": "application/json",
								"type": "text"
							}
						],
						"body": {
							"mode": "raw",
							"raw": "{\n\"heat\": 1.52536,\n\"type\": 3.1,\n\"tests\": [],\n\"material_grade\": 1.45637,\n \"properties\": {\n\t\"product_type\": \"Pipe\",\n\t\"length\": 11.273,\n\t\"weight\": 432.34,\n\t\"outerDiameter\": 273.1,\n\t\"thickness\": 6.3,\n\t\"batchLength\": 60.000,\n\t\"currentForm\": true\n },\n \"norm\": \"ASTM A23\",\n \"tp_UNS\": \"S32432\"\n}"
						},
						"url": {
							"raw": "http://localhost:5000/certificates",
							"protocol": "http",
							"host": [
								"localhost"
							],
							"port": "5000",
							"path": [
								"certificates"
							]
						}
					},
					"response": []
				},
				{
					"name": "Update",
					"request": {
						"method": "PUT",
						"header": [
							{
								"key": "Content-Type",
								"name": "Content-Type",
								"type": "text",
								"value": "application/json"
							}
						],
						"body": {
							"mode": "raw",
							"raw": "{\n\t\"tests\": [\"5d00b57f4b05df18b8b62c36\",\n    \"5d00b6724b05df18b8b62c84\"]\n}"
						},
						"url": {
							"raw": "http://localhost:5000/certificates/5d0c8d9fd12ed94231e0f25b/",
							"protocol": "http",
							"host": [
								"localhost"
							],
							"port": "5000",
							"path": [
								"certificates",
								"5d0c8d9fd12ed94231e0f25b",
								""
							]
						}
					},
					"response": []
				},
				{
					"name": "Update Properties",
					"request": {
						"method": "PUT",
						"header": [
							{
								"key": "X-Token-Jwt",
								"value": " eyJhbGciOiJIUzI1NiIsInR5cCI6IkpXVCJ9.eyJpZCI6IjVlMmVkNDc3ZDlhOTQwNDkzNjU3NTZhNCIsImZpcnN0bmFtZSI6ImR3dyIsImxhc3RuYW1lIjoiYXdkIiwicm9sZSI6IkFETUlOIiwiY29tcGFueSI6IjVlMmVkNDc3ZDlhOTQwNDkzNjU3NTZhNSIsImlhdCI6MTU4MjAzMDY1NiwiZXhwIjoxNTgyNzMwNjU2fQ.HM2Dz7qxEkWy2zfuanCprJfqTYy4_kyi-KOFM_5CZRM",
								"type": "text"
							}
						],
						"body": {
							"mode": "raw",
							"raw": "{\n\t\"newProperties\": {\n        \"diameter\" : 666,\n        \"secondDiameter\" : \"\",\n        \"firstOuterDiameter\" : \"\",\n        \"secondOuterDiameter\" : \"\",\n        \"firstThickness\" : \"\",\n        \"secondThickness\" : \"\",\n        \"productType\" : \"bend\",\n        \"length\" : \"\",\n        \"weight\" : \"\",\n        \"outerDiameter\" : \"\",\n        \"thickness\" : \"\",\n        \"batchLength\" : 666,\n        \"height\" : \"\"\n\t},\n\t\n\t\"oldProperties\": {\n\t    \"diameter\" : 444,\n\t    \"secondDiameter\" : null,\n\t    \"firstOuterDiameter\" : null,\n\t    \"secondOuterDiameter\" : null,\n\t    \"firstThickness\" : null,\n\t    \"secondThickness\" : null,\n\t    \"productType\" : \"bend\",\n\t    \"length\" : null,\n\t    \"weight\" : null,\n\t    \"outerDiameter\" : null,\n\t    \"thickness\" : null,\n\t    \"batchLength\" : 444,\n\t    \"height\" : null\n  \n\t}\n}"
						},
						"url": {
							"raw": "http://localhost:5000/certificates/5df8d9cf7a6b0a04adab4c33/productType",
							"protocol": "http",
							"host": [
								"localhost"
							],
							"port": "5000",
							"path": [
								"certificates",
								"5df8d9cf7a6b0a04adab4c33",
								"productType"
							]
						}
					},
					"response": []
				},
				{
					"name": "Update Properties Copy",
					"request": {
						"method": "POST",
						"header": [
							{
								"key": "Content-Type",
								"name": "Content-Type",
								"type": "text",
								"value": "application/json"
							},
							{
								"key": "X-Token-Jwt",
								"value": "eyJhbGciOiJIUzI1NiIsInR5cCI6IkpXVCJ9.eyJpZCI6IjVkZjM3NGU2ZjFjNWQ3NTY2NTMxYWNlOSIsImZpcnN0bmFtZSI6Ikh1aXZhbiIsImxhc3RuYW1lIjoiWXVyaWkiLCJyb2xlIjoiQURNSU4iLCJjb21wYW55IjoiNWRmMzc0ZTZmMWM1ZDc1NjY1MzFhY2VhIiwiaWF0IjoxNTc5MDg4NTU2LCJleHAiOjE1NzkxNzQ5NTZ9.ddHOLd0BHEl-u0zb2Cd1TQ0mjlRsixTlmCmWk_3gam0",
								"type": "text"
							}
						],
						"body": {
							"mode": "raw",
							"raw": "[\n\t5,\n\t5\n]"
						},
						"url": {
							"raw": "http://localhost:5000/certificates/5e1d7518f8524a13a6a9c6eb/split",
							"protocol": "http",
							"host": [
								"localhost"
							],
							"port": "5000",
							"path": [
								"certificates",
								"5e1d7518f8524a13a6a9c6eb",
								"split"
							]
						}
					},
					"response": []
				},
				{
					"name": "Batch Transfer",
					"request": {
						"method": "PUT",
						"header": [
							{
								"key": "Content-Type",
								"name": "Content-Type",
								"type": "text",
								"value": "application/json"
							},
							{
								"key": "X-Token-Jwt",
								"value": "eyJhbGciOiJIUzI1NiIsInR5cCI6IkpXVCJ9.eyJpZCI6IjVkZjBiNTUxODU2NGQ0MzZkZDA0MWJkMyIsImZpcnN0bmFtZSI6Im1hbiIsImxhc3RuYW1lIjoicm9uZG8iLCJyb2xlIjoiQURNSU4iLCJjb21wYW55IjoiNWRmMGI1NTE4NTY0ZDQzNmRkMDQxYmQ0IiwiaWF0IjoxNTc2NTA2OTQ1LCJleHAiOjE1NzY1OTMzNDV9.ctxDNxOrnKDk9jEN-yFgK8yKWO45_0_scJS0cJEMgL0",
								"type": "text"
							}
						],
						"body": {
							"mode": "raw",
							"raw": "{\n\t\"certificateIds\": [\"5df79532ea1a5d42b40599ff\", \"5df6964162673121db2c9783\"],\n\t\"certificates\": [\n\t\t{\n\t\t\t\"_id\": \"5df79532ea1a5d42b40599ff\",\n\t\t\t\"lineItem\": \"111\",\n\t\t\t\"projectId\": \"222\"\n\t\t\t\n\t\t},\n\t\t{\n\t\t\t\"_id\": \"5df6964162673121db2c9783\",\n\t\t\t\"lineItem\": \"333\",\n\t\t\t\"projectId\": \"444\"\n\t\t\t\n\t\t}\n\t],\n    \"orderNumber\": \"13FSAF4D\",\n    \"sender\": {\n    \t\"_id\": \"5df0b5518564d436dd041bd4\"\n    },\n    \"receiver\": {\n    \t\"_id\": \"5df374e6f1c5d7566531acea\",\n    \t\"mainLocation\": \"5d62ceed85ee2b1479577e98\"\n    }\n}"
						},
						"url": {
							"raw": "http://localhost:5000/certificates/transfer/all",
							"protocol": "http",
							"host": [
								"localhost"
							],
							"port": "5000",
							"path": [
								"certificates",
								"transfer",
								"all"
							]
						}
					},
					"response": []
				},
				{
					"name": "Delete",
					"request": {
						"method": "PUT",
						"header": [
							{
								"key": "Content-Type",
								"name": "Content-Type",
								"type": "text",
								"value": "application/json"
							},
							{
								"key": "X-Token-Jwt",
								"value": "eyJhbGciOiJIUzI1NiIsInR5cCI6IkpXVCJ9.eyJpZCI6IjVkZjBiNTUxODU2NGQ0MzZkZDA0MWJkMyIsImZpcnN0bmFtZSI6Im1hbiIsImxhc3RuYW1lIjoicm9uZG8iLCJyb2xlIjoiQURNSU4iLCJjb21wYW55IjoiNWRmMGI1NTE4NTY0ZDQzNmRkMDQxYmQ0IiwiaWF0IjoxNTc2NTA2OTQ1LCJleHAiOjE1NzY1OTMzNDV9.ctxDNxOrnKDk9jEN-yFgK8yKWO45_0_scJS0cJEMgL0",
								"type": "text"
							}
						],
						"body": {
							"mode": "raw",
							"raw": "{\n\t\"certificateIds\": [\"5df79532ea1a5d42b40599ff\", \"5df6964162673121db2c9783\"],\n\t\"certificates\": [\n\t\t{\n\t\t\t\"_id\": \"5df79532ea1a5d42b40599ff\",\n\t\t\t\"lineItem\": \"111\",\n\t\t\t\"projectId\": \"222\"\n\t\t\t\n\t\t},\n\t\t{\n\t\t\t\"_id\": \"5df6964162673121db2c9783\",\n\t\t\t\"lineItem\": \"333\",\n\t\t\t\"projectId\": \"444\"\n\t\t\t\n\t\t}\n\t],\n    \"orderNumber\": \"13FSAF4D\",\n    \"sender\": {\n    \t\"_id\": \"5df0b5518564d436dd041bd4\"\n    },\n    \"receiver\": {\n    \t\"_id\": \"5df374e6f1c5d7566531acea\",\n    \t\"mainLocation\": \"5d62ceed85ee2b1479577e98\"\n    }\n}"
						},
						"url": {
							"raw": "http://localhost:5000/certificates/transfer/all",
							"protocol": "http",
							"host": [
								"localhost"
							],
							"port": "5000",
							"path": [
								"certificates",
								"transfer",
								"all"
							]
						}
					},
					"response": []
				},
				{
					"name": "Single",
					"protocolProfileBehavior": {
						"disableBodyPruning": true
					},
					"request": {
						"method": "GET",
						"header": [
							{
								"key": "X-Token-Jwt",
								"value": " eyJhbGciOiJIUzI1NiIsInR5cCI6IkpXVCJ9.eyJpZCI6IjVlMmVkNDc3ZDlhOTQwNDkzNjU3NTZhNCIsImZpcnN0bmFtZSI6ImR3dyIsImxhc3RuYW1lIjoiYXdkIiwicm9sZSI6IkFETUlOIiwiY29tcGFueSI6IjVlMmVkNDc3ZDlhOTQwNDkzNjU3NTZhNSIsImlhdCI6MTU4MjAzMDY1NiwiZXhwIjoxNTgyNzMwNjU2fQ.HM2Dz7qxEkWy2zfuanCprJfqTYy4_kyi-KOFM_5CZRM",
								"type": "text"
							}
						],
						"body": {
							"mode": "raw",
							"raw": "{\n\"heat\": 1.52536,\n\"type\": 3.2,\n\"material_grade\": 1.45637,\n\"tests\": [\"5ccc1e0ad82209394497d796\"],\n \"properties\": {\n  \"product_type\": \"Pipe\",\n     \"length\": 11.273,\n     \"weight\": 432.34,\n     \"outerDiameter\": 273.1,\n     \"thickness\": 6.3,\n     \"batchLength\": 60.000,\n     \"currentForm\": true\n },\n \"norm\": \"ASTM A23\",\n \"tp_UNS\": \"S32432\"\n \n}"
						},
						"url": {
							"raw": "{{host}}/certificates/5e45a246e0354054b131a09d",
							"host": [
								"{{host}}"
							],
							"path": [
								"certificates",
								"5e45a246e0354054b131a09d"
							]
						}
					},
					"response": []
				},
				{
					"name": "List",
					"protocolProfileBehavior": {
						"disableBodyPruning": true
					},
					"request": {
						"auth": {
							"type": "basic",
							"basic": [
								{
									"key": "username",
									"value": "https://blockchain.steeltrace.eu",
									"type": "string"
								},
								{
									"key": "password",
									"value": "dFgZfpcMULc6mrun8Be5WN9q4cJ",
									"type": "string"
								}
							]
						},
						"method": "GET",
						"header": [
							{
								"key": "x-token-jwt",
								"value": "eyJhbGciOiJIUzI1NiIsInR5cCI6IkpXVCJ9.eyJpZCI6IjVkNTVkM2QwY2QzMjBmMmI4MmNhM2NhOSIsImZpcnN0bmFtZSI6InJvbmRvMzQiLCJsYXN0bmFtZSI6Im1hbjEyIiwicm9sZSI6IlNVUEVSX0FETUlOIiwiY29tcGFueSI6IjVkNTVkNDA5Y2QzMjBmMmI4MmNhM2NhYSIsImlhdCI6MTU4MzMzMzk1MCwiZXhwIjoxNTg0MDMzOTUwfQ.6EFNfEZP4DrfbYWgT18E3d0KdPfBz1p5y4oskx_ICZY",
								"type": "text"
							}
						],
						"body": {
							"mode": "raw",
							"raw": "{\n\"heat\": 1.52536,\n\"type\": 3.1,\n\"material_grade\": 1.45637,\n \"properties\": {\n  \"product_type\": \"Pipe\",\n     \"length\": 11.273,\n     \"weight\": 432.34,\n     \"outerDiameter\": 273.1,\n     \"thickness\": 6.3,\n     \"batchLength\": 60.000,\n     \"currentForm\": true\n },\n \"norm\": \"ASTM A23\",\n \"tp_UNS\": \"S32432\"\n \n}"
						},
						"url": {
							"raw": "{{host}}/certificates?companyId=5e2ed477d9a94049365756a5",
							"host": [
								"{{host}}"
							],
							"path": [
								"certificates"
							],
							"query": [
								{
									"key": "companyId",
									"value": "5e2ed477d9a94049365756a5"
								}
							]
						}
					},
					"response": []
				},
				{
					"name": "Migrations",
					"protocolProfileBehavior": {
						"disableBodyPruning": true
					},
					"request": {
						"auth": {
							"type": "basic",
							"basic": [
								{
									"key": "username",
									"value": "https://blockchain.steeltrace.eu",
									"type": "string"
								},
								{
									"key": "password",
									"value": "dFgZfpcMULc6mrun8Be5WN9q4cJ",
									"type": "string"
								}
							]
						},
						"method": "GET",
						"header": [
							{
								"key": "x-token-jwt",
								"type": "text",
								"value": "eyJhbGciOiJIUzI1NiIsInR5cCI6IkpXVCJ9.eyJpZCI6IjVkNTVkM2QwY2QzMjBmMmI4MmNhM2NhOSIsImZpcnN0bmFtZSI6InJvbmRvMzQiLCJsYXN0bmFtZSI6Im1hbjEyIiwicm9sZSI6IlNVUEVSX0FETUlOIiwiY29tcGFueSI6IjVkNTVkNDA5Y2QzMjBmMmI4MmNhM2NhYSIsImlhdCI6MTU4MzMzMzk1MCwiZXhwIjoxNTg0MDMzOTUwfQ.6EFNfEZP4DrfbYWgT18E3d0KdPfBz1p5y4oskx_ICZY"
							}
						],
						"body": {
							"mode": "raw",
							"raw": "{\n\"heat\": 1.52536,\n\"type\": 3.1,\n\"material_grade\": 1.45637,\n \"properties\": {\n  \"product_type\": \"Pipe\",\n     \"length\": 11.273,\n     \"weight\": 432.34,\n     \"outerDiameter\": 273.1,\n     \"thickness\": 6.3,\n     \"batchLength\": 60.000,\n     \"currentForm\": true\n },\n \"norm\": \"ASTM A23\",\n \"tp_UNS\": \"S32432\"\n \n}"
						},
						"url": {
							"raw": "{{host}}/migrations",
							"host": [
								"{{host}}"
							],
							"path": [
								"migrations"
							]
						}
					},
					"response": []
				},
				{
					"name": "Search",
					"protocolProfileBehavior": {
						"disableBodyPruning": true
					},
					"request": {
						"method": "GET",
						"header": [
							{
								"key": "Content-Type",
								"value": "application/json",
								"type": "text"
							},
							{
								"key": "X-Token-Jwt",
								"value": " eyJhbGciOiJIUzI1NiIsInR5cCI6IkpXVCJ9.eyJpZCI6IjVkNTVkM2QwY2QzMjBmMmI4MmNhM2NhOSIsImZpcnN0bmFtZSI6InJvbmRvIiwibGFzdG5hbWUiOiJtYW4iLCJyb2xlIjoiQURNSU4iLCJjb21wYW55IjoiNWQ1NWQ0MDljZDMyMGYyYjgyY2EzY2FhIiwiaWF0IjoxNTY5NDc3Nzc5LCJleHAiOjE1Njk1NjQxNzl9.eQUGAbAuWjDhK2xAD7lXYRx9QVsJFRaKMBSWKIsd0MM",
								"type": "text"
							}
						],
						"body": {
							"mode": "raw",
							"raw": "{\n    \"query\": {\n        \"match_phrase_prefix\" : {\n            \"material_grade\": {\n                \"query\": \"1\",\n                \"slop\": 3,\n                \"max_expansions\": 10\n            }\n        }\n    },\n    \"_source\": [ \"material_grade\"]\n}",
							"options": {
								"raw": {
									"language": "json"
								}
							}
						},
						"url": {
							"raw": "{{host}}/certificates/search",
							"host": [
								"{{host}}"
							],
							"path": [
								"certificates",
								"search"
							]
						}
					},
					"response": []
				}
			]
		},
		{
			"name": "Transactions",
			"item": [
				{
					"name": "Create",
					"request": {
						"method": "POST",
						"header": [
							{
								"key": "X-Token-Jwt",
								"value": " eyJhbGciOiJIUzI1NiIsInR5cCI6IkpXVCJ9.eyJpZCI6IjVlMmVkNDc3ZDlhOTQwNDkzNjU3NTZhNCIsImZpcnN0bmFtZSI6ImR3dyIsImxhc3RuYW1lIjoiYXdkIiwicm9sZSI6IkFETUlOIiwiY29tcGFueSI6IjVlMmVkNDc3ZDlhOTQwNDkzNjU3NTZhNSIsImlhdCI6MTU4MTUxMDY5NywiZXhwIjoxNTgxNTk3MDk3fQ.oTJv9abBcuiA9LkF7WW-YPKQ-I4BlX6JXkLH6-0VZvw",
								"type": "text"
							}
						],
						"body": {
							"mode": "raw",
							"raw": "{\n\t\"type\": \"certificate\",\n\t\"referenceId\": \"5d11fdaaaf3c9f340db4fab3\",\n\t\"signed\": true,\n\t\"signature\": \"1f345knb2bdk34a5d32\",\n\t\"creator\": \"5c7e3bced3aef23d90990912\",\n\t\"signer\": \"5c7e3bcdd3aef23d90990910\"\n}"
						},
						"url": {
							"raw": "http://localhost:5000/transactions",
							"protocol": "http",
							"host": [
								"localhost"
							],
							"port": "5000",
							"path": [
								"transactions"
							]
						}
					},
					"response": []
				},
				{
					"name": "Broadcast",
					"request": {
						"method": "POST",
						"header": [
							{
								"key": "Content-Type",
								"name": "Content-Type",
								"type": "text",
								"value": "application/json"
							}
						],
						"body": {
							"mode": "raw",
							"raw": "{\n  \"hash\": \"0xf8c580808347b76094c21ccf3a67a92af3b32e2f388979c1ab4ce6e22580b864cb05462c3563663466656331656366666239336437626535623731620000000000000000000000000000000000000000000000000000000000000000000000000000004000000000000000000000000000000000000000000000000000000000000000001ba0f7d3516f107cd88f30941adaef35956638460a4ba08348c75874842fabf2c8cba03dfac7136eb32e02645ed56ffcbf8c33d74967f64dfb445d95a83194e44ffda1\"\n}"
						},
						"url": {
							"raw": "http://localhost:5000/transactions/broadcast",
							"protocol": "http",
							"host": [
								"localhost"
							],
							"port": "5000",
							"path": [
								"transactions",
								"broadcast"
							]
						}
					},
					"response": []
				},
				{
					"name": "Get nonce",
					"protocolProfileBehavior": {
						"disableBodyPruning": true
					},
					"request": {
						"method": "GET",
						"header": [
							{
								"key": "Content-Type",
								"name": "Content-Type",
								"type": "text",
								"value": "application/json"
							}
						],
						"body": {
							"mode": "raw",
							"raw": "{\n  \"signed\": true,\n  \"signature\": \"1f345knb2bdk34a5d32\",\n  \"creator\": \"5c7e3bced3aef23d90990912\",\n  \"signer\": \"5c7e3bcdd3aef23d90990910\"\n}"
						},
						"url": {
							"raw": "http://localhost:5000/transactions/nonce/0x8c8B682110A59c6363042227FC8C1be29C41Af37",
							"protocol": "http",
							"host": [
								"localhost"
							],
							"port": "5000",
							"path": [
								"transactions",
								"nonce",
								"0x8c8B682110A59c6363042227FC8C1be29C41Af37"
							]
						}
					},
					"response": []
				},
				{
					"name": "List",
					"request": {
						"method": "GET",
						"header": [
							{
								"key": "X-Token-Jwt",
								"value": " eyJhbGciOiJIUzI1NiIsInR5cCI6IkpXVCJ9.eyJpZCI6IjVlMmVkNDc3ZDlhOTQwNDkzNjU3NTZhNCIsImZpcnN0bmFtZSI6ImR3dyIsImxhc3RuYW1lIjoiYXdkIiwicm9sZSI6IkFETUlOIiwiY29tcGFueSI6IjVlMmVkNDc3ZDlhOTQwNDkzNjU3NTZhNSIsImlhdCI6MTU4MTQ5NjU4NiwiZXhwIjoxNTgxNTgyOTg2fQ.bipMMK6BXar2m2saVcAnGEwmlRZAfglXd8wq7o77LtQ",
								"type": "text"
							}
						],
						"url": {
							"raw": "{{host}}/transactions",
							"host": [
								"{{host}}"
							],
							"path": [
								"transactions"
							]
						}
					},
					"response": []
				}
			]
		},
		{
			"name": "Companies",
			"item": [
				{
					"name": "Create",
					"request": {
						"method": "POST",
						"header": [
							{
								"key": "Content-Type",
								"name": "Content-Type",
								"value": "application/json",
								"type": "text"
							},
							{
								"key": "X-Token-Jwt",
								"value": "eyJhbGciOiJIUzI1NiIsInR5cCI6IkpXVCJ9.eyJpZCI6IjVkMzcxYWI1YjA4MWE0NDAzZTRiZjg1MSIsImZpcnN0bmFtZSI6IlNtaXRoIiwibGFzdG5hbWUiOiJKb2huIiwicm9sZSI6IkFETUlOIiwiY29tcGFueSI6IjVkMzcxYWI1YjA4MWE0NDAzZTRiZjg1MyIsImlhdCI6MTU2NTg2OTYyNywiZXhwIjoxNTY1ODczMjI3fQ.fJwJqvnvlzX9AHK6dcidkZe0XWBOAjHOq8jIr98WSaA",
								"type": "text"
							}
						],
						"body": {
							"mode": "raw",
							"raw": "{\n\t  \"modules\": [\"5c8fbf6f3a48cc33652b4271\"],\n\t  \"locations\": [{\n          \"address_street\": \"Hazendanslaan\",\n\t      \"address_postal_code\": \"6215JA\",\n\t      \"address_city\": \"Maastricht\",\n\t      \"address_house_number\": \"2\",\n\t      \"phone\": \"0031614379205\"\n       }],\n       \"admin\": {\"_id\": \"5d55477596a4333aea09c5ce\"},\n\t  \"account_active\": true,\n\t  \"owner\": \"5d55477596a4333aea09c5ce\"\n}"
						},
						"url": {
							"raw": "http://localhost:5000/companies",
							"protocol": "http",
							"host": [
								"localhost"
							],
							"port": "5000",
							"path": [
								"companies"
							]
						}
					},
					"response": []
				},
				{
					"name": "Delete",
					"request": {
						"method": "DELETE",
						"header": [
							{
								"key": "X-Token-Jwt",
								"value": " eyJhbGciOiJIUzI1NiIsInR5cCI6IkpXVCJ9.eyJpZCI6IjVlODJjNjg3YjIzMWFiMDAzYmY2NDJkZCIsImZpcnN0bmFtZSI6Ik5lbGxhIiwibGFzdG5hbWUiOiJMaXR0bGUiLCJyb2xlIjoiU1VQRVJfQURNSU4iLCJjb21wYW55IjoiNWU4MmM2ODdiMjMxYWIwMDNiZjY0MmRlIiwiaWF0IjoxNTg4MjU0NzQ0LCJleHAiOjE1ODg5NTQ3NDR9.ni1yGCzecbmyl7sEKfKXQPxqaYFRMQgMD8-lFStKPIM",
								"type": "text"
							}
						],
						"body": {
							"mode": "raw",
							"raw": "{\n\t  \"modules\": [\"5c8fbf6f3a48cc33652b4271\"],\n\t  \"locations\": [{\n          \"address_street\": \"Hazendanslaan\",\n\t      \"address_postal_code\": \"6215JA\",\n\t      \"address_city\": \"Maastricht\",\n\t      \"address_house_number\": \"2\",\n\t      \"phone\": \"0031614379205\"\n       }],\n       \"admin\": {\"_id\": \"5d55477596a4333aea09c5ce\"},\n\t  \"account_active\": true,\n\t  \"owner\": \"5d55477596a4333aea09c5ce\"\n}"
						},
						"url": {
							"raw": "http://localhost:5000/companies/5e82dac8e9548b003dd9ae38",
							"protocol": "http",
							"host": [
								"localhost"
							],
							"port": "5000",
							"path": [
								"companies",
								"5e82dac8e9548b003dd9ae38"
							]
						}
					},
					"response": []
				},
				{
					"name": "Update",
					"request": {
						"method": "PUT",
						"header": [
							{
								"key": "Content-Type",
								"name": "Content-Type",
								"type": "text",
								"value": "application/json"
							}
						],
						"body": {
							"mode": "raw",
							"raw": "{\n\t  \"main_location\": {\n\t  \t  \"address_street\": \"fffffff\",\n\t      \"address_postal_code\": \"31123234\",\n\t      \"address_city\": \"awdawd\",\n\t      \"address_house_number\": \"2dw\",\n\t      \"phone\": \"2131231\"\n\t  }\n}"
						},
						"url": {
							"raw": "{{host}}/companies/5d2c558c451390221ff01f55",
							"host": [
								"{{host}}"
							],
							"path": [
								"companies",
								"5d2c558c451390221ff01f55"
							]
						}
					},
					"response": []
				},
				{
					"name": "List",
					"protocolProfileBehavior": {
						"disableBodyPruning": true
					},
					"request": {
						"method": "GET",
						"header": [
							{
								"key": "Content-Type",
								"name": "Content-Type",
								"type": "text",
								"value": "application/json"
							}
						],
						"body": {
							"mode": "raw",
							"raw": "{\n\t  \"employees\": [\"5cee3bab820dcf214dfbf437\"],\n\t  \"modules\": [\"5c7e3b1ad3aef23d9099090f\"],\n\t  \"locations\": [{\n          \"address_street\": \"Hazendanslaan\",\n\t      \"address_postal_code\": \"6215JA\",\n\t      \"address_city\": \"Maastricht\",\n\t      \"address_house_number\": \"2\",\n\t      \"phone\": \"0031614379205\"\n       }],\n\t  \"account_active\": true,\n\t  \"owner\": \"5cee3bab820dcf214dfbf437\"\n}"
						},
						"url": {
							"raw": "{{host}}/companies",
							"host": [
								"{{host}}"
							],
							"path": [
								"companies"
							]
						}
					},
					"response": []
				},
				{
					"name": "Single",
					"protocolProfileBehavior": {
						"disableBodyPruning": true
					},
					"request": {
						"method": "GET",
						"header": [
							{
								"key": "X-Token-Jwt",
								"value": " eyJhbGciOiJIUzI1NiIsInR5cCI6IkpXVCJ9.eyJpZCI6IjVlMmVkNDc3ZDlhOTQwNDkzNjU3NTZhNCIsImZpcnN0bmFtZSI6ImR3dyIsImxhc3RuYW1lIjoiYXdkIiwicm9sZSI6IkFETUlOIiwiY29tcGFueSI6IjVlMmVkNDc3ZDlhOTQwNDkzNjU3NTZhNSIsImlhdCI6MTU4MTQwOTk4NCwiZXhwIjoxNTgxNDk2Mzg0fQ.8PSNpahloRp1McOoyDdQoETxIdGR4U6JcUQoP-FjtgU",
								"type": "text"
							}
						],
						"body": {
							"mode": "raw",
							"raw": "{\n\t  \"employees\": [\"5cee3bab820dcf214dfbf437\"],\n\t  \"modules\": [\"5c7e3b1ad3aef23d9099090f\"],\n\t  \"locations\": [{\n          \"address_street\": \"Hazendanslaan\",\n\t      \"address_postal_code\": \"6215JA\",\n\t      \"address_city\": \"Maastricht\",\n\t      \"address_house_number\": \"2\",\n\t      \"phone\": \"0031614379205\"\n       }],\n\t  \"account_active\": true,\n\t  \"owner\": \"5cee3bab820dcf214dfbf437\"\n}"
						},
						"url": {
							"raw": "{{host}}/companies/5d6e1ba9f696061b59c326e4",
							"host": [
								"{{host}}"
							],
							"path": [
								"companies",
								"5d6e1ba9f696061b59c326e4"
							]
						}
					},
					"response": []
				},
				{
					"name": "Tests",
					"protocolProfileBehavior": {
						"disableBodyPruning": true
					},
					"request": {
						"method": "GET",
						"header": [
							{
								"key": "Content-Type",
								"name": "Content-Type",
								"type": "text",
								"value": "application/json"
							}
						],
						"body": {
							"mode": "raw",
							"raw": "{\n\t  \"employees\": [\"5cee3bab820dcf214dfbf437\"],\n\t  \"modules\": [\"5c7e3b1ad3aef23d9099090f\"],\n\t  \"locations\": [{\n          \"address_street\": \"Hazendanslaan\",\n\t      \"address_postal_code\": \"6215JA\",\n\t      \"address_city\": \"Maastricht\",\n\t      \"address_house_number\": \"2\",\n\t      \"phone\": \"0031614379205\"\n       }],\n\t  \"account_active\": true,\n\t  \"owner\": \"5cee3bab820dcf214dfbf437\"\n}"
						},
						"url": {
							"raw": "http://localhost:5000/companies/5d371ab5b081a4403e4bf853/tests?limit=10&offset=0",
							"protocol": "http",
							"host": [
								"localhost"
							],
							"port": "5000",
							"path": [
								"companies",
								"5d371ab5b081a4403e4bf853",
								"tests"
							],
							"query": [
								{
									"key": "limit",
									"value": "10"
								},
								{
									"key": "offset",
									"value": "0"
								}
							]
						}
					},
					"response": []
				},
				{
					"name": "Upgrade",
					"request": {
						"method": "POST",
						"header": [
							{
								"key": "Content-Type",
								"type": "text",
								"value": "application/json"
							},
							{
								"key": "X-Token-Jwt",
								"type": "text",
								"value": "eyJhbGciOiJIUzI1NiIsInR5cCI6IkpXVCJ9.eyJpZCI6IjVlODJjNjg3YjIzMWFiMDAzYmY2NDJkZCIsImZpcnN0bmFtZSI6Ik5lbGxhIiwibGFzdG5hbWUiOiJMaXR0bGUiLCJyb2xlIjoiU1VQRVJfQURNSU4iLCJjb21wYW55IjoiNWU4MmM2ODdiMjMxYWIwMDNiZjY0MmRlIiwiaWF0IjoxNTg4Nzc0NzcyLCJleHAiOjE1ODk0NzQ3NzJ9.YI2-rgTwkEbeTmA_I1k8Y4-z8i-nT1ulSqjUcrw0NWc"
							}
						],
						"body": {
							"mode": "raw",
							"raw": "{\n\t\"email\": \"uramen12@gmail.com\"\n}"
						},
						"url": {
							"raw": "{{host}}/companies/upgrade",
							"host": [
								"{{host}}"
							],
							"path": [
								"companies",
								"upgrade"
							]
						}
					},
					"response": []
				}
			]
		},
		{
			"name": "Account",
			"item": [
				{
					"name": "Me",
					"request": {
						"method": "GET",
						"header": [],
						"url": {
							"raw": "http://localhost:5000/account/users/me",
							"protocol": "http",
							"host": [
								"localhost"
							],
							"port": "5000",
							"path": [
								"account",
								"users",
								"me"
							]
						}
					},
					"response": []
				},
				{
					"name": "Change password",
					"request": {
						"method": "PUT",
						"header": [
							{
								"key": "Content-Type",
								"name": "Content-Type",
								"value": "application/json",
								"type": "text"
							},
							{
								"key": "X-Token-Jwt",
								"value": "eyJhbGciOiJIUzI1NiIsInR5cCI6IkpXVCJ9.eyJpZCI6IjVkZjM3NGU2ZjFjNWQ3NTY2NTMxYWNlOSIsImZpcnN0bmFtZSI6Ikh1aXZhbiIsImxhc3RuYW1lIjoiWXVyaWkiLCJyb2xlIjoiQURNSU4iLCJjb21wYW55IjoiNWRmMzc0ZTZmMWM1ZDc1NjY1MzFhY2VhIiwiaWF0IjoxNTc2Njc2MTg3LCJleHAiOjE1NzY3NjI1ODd9.4OtV8qyJ8d_5SJUYP2V20zYXlxrj8yWX9DeS0efDWD8",
								"type": "text"
							}
						],
						"body": {
							"mode": "raw",
							"raw": "{\n\t\"oldPassword\": \"2222\",\n\t\"newPassword\": \"1111\"\n}",
							"options": {
								"raw": {
									"language": "json"
								}
							}
						},
						"url": {
							"raw": "http://localhost:5000/account/password",
							"protocol": "http",
							"host": [
								"localhost"
							],
							"port": "5000",
							"path": [
								"account",
								"password"
							]
						}
					},
					"response": []
				},
				{
					"name": "Users",
					"request": {
						"method": "GET",
						"header": [
							{
								"key": "X-Token-Jwt",
								"value": "eyJhbGciOiJIUzI1NiIsInR5cCI6IkpXVCJ9.eyJpZCI6IjVlMDVmOTBlYzQzYzBiMmNmMmMxNzc1MCIsImZpcnN0bmFtZSI6IjExMTExIiwibGFzdG5hbWUiOiIxMTExMSIsInJvbGUiOiJBRE1JTiIsImNvbXBhbnkiOiI1ZTA1ZjkwZWM0M2MwYjJjZjJjMTc3NTEiLCJpYXQiOjE1Nzk1MTU4ODEsImV4cCI6MTU3OTYwMjI4MX0.ob6CXNiAMbDI_cn47KG0cD-fe6mOyYXkJ7KqGQ_Ll-Y",
								"type": "text"
							}
						],
						"url": {
							"raw": "{{host}}/account/users",
							"host": [
								"{{host}}"
							],
							"path": [
								"account",
								"users"
							]
						}
					},
					"response": []
				},
				{
					"name": "Register",
					"request": {
						"method": "POST",
						"header": [
							{
								"key": "Content-Type",
								"value": "application/json",
								"type": "text"
							},
							{
								"key": "X-Token-Jwt",
								"value": "eyJhbGciOiJIUzI1NiIsInR5cCI6IkpXVCJ9.eyJpZCI6IjVkNTVkM2QwY2QzMjBmMmI4MmNhM2NhOSIsImZpcnN0bmFtZSI6IlRvbSIsImxhc3RuYW1lIjoiTWV1bGVuZGlqa3MiLCJyb2xlIjoiQURNSU4iLCJjb21wYW55IjoiNWQ1NWQ0MDljZDMyMGYyYjgyY2EzY2FhIiwiaWF0IjoxNTY2NTU3MTM5LCJleHAiOjE1NjY1NjA3Mzl9.fxF6wKsZUlo7NvQwBGz0yJtfxZ02RUzJcIei5vbYwdk",
								"type": "text",
								"disabled": true
							}
						],
						"body": {
							"mode": "raw",
							"raw": "{\n\t\"user\": {\n    \"lastname\": \"Super\",\n    \"firstname\": \"Odmen\",\n    \"role\": \"SUPER_ADMIN\",\n    \"username\": \"steeltrace\",\n    \"password\": \"dFgZfpcMULc6mrun8Be5WN9q4cJApi\"\n\t},\n\t\n\t\"company\": {\n\t  \"modules\": [\"5d2ca133eeb4e0001b502c9d\"],\n\t  \"name\": \"Sapient SA\",\n\t   \"mainLocation\": {\n          \"street\": \"Hazendanslaan\",\n\t      \"postalCode\": \"6215JA\",\n\t      \"addressCity\": \"Maastricht\",\n\t      \"houseNumber\": \"2\",\n\t      \"phone\": \"0031614379205\"\n       },\n       \n\t  \"locations\": [{\n          \"street\": \"Hazendanslaan\",\n\t      \"postalCode\": \"6215JA\",\n\t      \"addressCity\": \"Maastricht\",\n\t      \"houseNumber\": \"2\",\n\t      \"phone\": \"0031614379205\"\n       }]\n\t}\n}\n"
						},
						"url": {
							"raw": "{{host}}/account/register",
							"host": [
								"{{host}}"
							],
							"path": [
								"account",
								"register"
							]
						}
					},
					"response": []
				},
				{
					"name": "Add user",
					"request": {
						"method": "POST",
						"header": [
							{
								"key": "Content-Type",
								"type": "text",
								"value": "application/json"
							},
							{
								"key": "X-Token-Jwt",
								"type": "text",
								"value": "eyJhbGciOiJIUzI1NiIsInR5cCI6IkpXVCJ9.eyJpZCI6IjVlMDVmOTBlYzQzYzBiMmNmMmMxNzc1MCIsImZpcnN0bmFtZSI6IjExMTExIiwibGFzdG5hbWUiOiIxMTExMSIsInJvbGUiOiJBRE1JTiIsImNvbXBhbnkiOiI1ZTA1ZjkwZWM0M2MwYjJjZjJjMTc3NTEiLCJpYXQiOjE1Nzk2MDU1NzAsImV4cCI6MTU3OTY5MTk3MH0.uJ9gWuVGMuIJcQbpLMxdR9b7LxcE74OUSkoX891Oy6E"
							}
						],
						"body": {
							"mode": "raw",
							"raw": "{\n\t\"lastname\": \"Smith\",\n\t\"firstname\": \"John\",\n\t\"role\": \"PRODUCER\",\n\t\"username\": \"123123\",\n\t\"password\": \"wjky5WzK28SySHQ6Kzs7\"\n}\n"
						},
						"url": {
							"raw": "{{host}}/account/users",
							"host": [
								"{{host}}"
							],
							"path": [
								"account",
								"users"
							]
						}
					},
					"response": []
				},
				{
					"name": "Login",
					"request": {
						"method": "POST",
						"header": [
							{
								"key": "Content-Type",
								"name": "Content-Type",
								"value": "application/json",
								"type": "text"
							}
						],
						"body": {
							"mode": "raw",
							"raw": "{\n\t\"username\": \"inum\",\n\t\"password\": \"1111\"\n}\n"
						},
						"url": {
							"raw": "{{host}}/account/login",
							"host": [
								"{{host}}"
							],
							"path": [
								"account",
								"login"
							]
						}
					},
					"response": []
				},
				{
					"name": "RestoreWallet",
					"request": {
						"method": "POST",
						"header": [
							{
								"key": "Content-Type",
								"name": "Content-Type",
								"type": "text",
								"value": "application/json"
							}
						],
						"body": {
							"mode": "raw",
							"raw": "{\n\t\"address\": \"0x5FfA993ee91A125963f4662Ee8A7694744281eB5\"\n}\n"
						},
						"url": {
							"raw": "{{host}}/account/restoreWallet",
							"host": [
								"{{host}}"
							],
							"path": [
								"account",
								"restoreWallet"
							]
						}
					},
					"response": []
				},
				{
					"name": "Add modules",
					"request": {
						"method": "PUT",
						"header": [
							{
								"key": "Content-Type",
								"name": "Content-Type",
								"value": "application/json",
								"type": "text"
							}
						],
						"body": {
							"mode": "raw",
							"raw": "{\n\n    \"modules\": [\"5d2ca133eeb4e0001b502c9d\", \"5d2ca171eeb4e0001b502c9f\"]\n  }"
						},
						"url": {
							"raw": "{{host}}/account/company",
							"host": [
								"{{host}}"
							],
							"path": [
								"account",
								"company"
							]
						}
					},
					"response": []
				},
				{
					"name": "Get User",
					"request": {
						"method": "GET",
						"header": [],
						"url": {
							"raw": "{{host}}/account/users/5d6cdbc7aea03125f4e14a6b",
							"host": [
								"{{host}}"
							],
							"path": [
								"account",
								"users",
								"5d6cdbc7aea03125f4e14a6b"
							]
						}
					},
					"response": []
				}
			],
			"event": [
				{
					"listen": "prerequest",
					"script": {
						"id": "6f970ebb-24a7-4d03-9a5a-a5d7f3d757f5",
						"type": "text/javascript",
						"exec": [
							""
						]
					}
				},
				{
					"listen": "test",
					"script": {
						"id": "46999ff0-ba60-4452-bbf8-c40d5a95a369",
						"type": "text/javascript",
						"exec": [
							""
						]
					}
				}
			]
		},
		{
			"name": "Modules",
			"item": [
				{
					"name": "Create",
					"request": {
						"method": "POST",
						"header": [
							{
								"key": "Content-Type",
								"name": "Content-Type",
								"value": "application/json",
								"type": "text"
							}
						],
						"body": {
							"mode": "raw",
							"raw": "{\n    \"name\": \"Producer\"\n }"
						},
						"url": {
							"raw": "{{host}}/modules/new",
							"host": [
								"{{host}}"
							],
							"path": [
								"modules",
								"new"
							]
						}
					},
					"response": []
				},
				{
					"name": "List",
					"protocolProfileBehavior": {
						"disableBodyPruning": true
					},
					"request": {
						"method": "GET",
						"header": [
							{
								"key": "Content-Type",
								"name": "Content-Type",
								"type": "text",
								"value": "application/json"
							}
						],
						"body": {
							"mode": "raw",
							"raw": "{\n    \"name\": \"Producer\"\n  }"
						},
						"url": {
							"raw": "{{host}}/modules",
							"host": [
								"{{host}}"
							],
							"path": [
								"modules"
							]
						}
					},
					"response": []
				}
			]
		},
		{
			"name": "Blockchain",
			"item": [
				{
					"name": "Certificates",
					"request": {
						"method": "GET",
						"header": [
							{
								"key": "X-Token-Jwt",
								"value": " eyJhbGciOiJIUzI1NiIsInR5cCI6IkpXVCJ9.eyJpZCI6IjVlMmVkNDc3ZDlhOTQwNDkzNjU3NTZhNCIsImZpcnN0bmFtZSI6ImR3dyIsImxhc3RuYW1lIjoiYXdkIiwicm9sZSI6IkFETUlOIiwiY29tcGFueSI6IjVlMmVkNDc3ZDlhOTQwNDkzNjU3NTZhNSIsImlhdCI6MTU4MDk4NDk0NSwiZXhwIjoxNTgxMDcxMzQ1fQ.W8ABPIBiU8LA_QmtE10LhIAWFxYizS7KHutHpgtxKyM",
								"type": "text"
							}
						],
						"url": {
							"raw": "http://localhost:5000/blockchain/certificates/5e3c012cf14aee2650c56766",
							"protocol": "http",
							"host": [
								"localhost"
							],
							"port": "5000",
							"path": [
								"blockchain",
								"certificates",
								"5e3c012cf14aee2650c56766"
							]
						}
					},
					"response": []
				},
				{
					"name": "Get Test",
					"request": {
						"method": "GET",
						"header": [
							{
								"key": "X-Token-Jwt",
								"value": " eyJhbGciOiJIUzI1NiIsInR5cCI6IkpXVCJ9.eyJpZCI6IjVlMmVkNDc3ZDlhOTQwNDkzNjU3NTZhNCIsImZpcnN0bmFtZSI6ImR3dyIsImxhc3RuYW1lIjoiYXdkIiwicm9sZSI6IkFETUlOIiwiY29tcGFueSI6IjVlMmVkNDc3ZDlhOTQwNDkzNjU3NTZhNSIsImlhdCI6MTU4MDk4NDk0NSwiZXhwIjoxNTgxMDcxMzQ1fQ.W8ABPIBiU8LA_QmtE10LhIAWFxYizS7KHutHpgtxKyM",
								"type": "text"
							}
						],
						"url": {
							"raw": "http://localhost:5000/blockchain/tests/5e3bfa10f14aee2650c56723",
							"protocol": "http",
							"host": [
								"localhost"
							],
							"port": "5000",
							"path": [
								"blockchain",
								"tests",
								"5e3bfa10f14aee2650c56723"
							]
						}
					},
					"response": []
				},
				{
					"name": "Companies",
					"request": {
						"method": "GET",
						"header": [],
						"url": {
							"raw": "{{host}}/blockchain/companies",
							"host": [
								"{{host}}"
							],
							"path": [
								"blockchain",
								"companies"
							]
						}
					},
					"response": []
				},
				{
					"name": "Company Users",
					"request": {
						"method": "GET",
						"header": [
							{
								"key": "X-Token-Jwt",
								"value": " eyJhbGciOiJIUzI1NiIsInR5cCI6IkpXVCJ9.eyJpZCI6IjVlMmVkNDc3ZDlhOTQwNDkzNjU3NTZhNCIsImZpcnN0bmFtZSI6ImR3dyIsImxhc3RuYW1lIjoiYXdkIiwicm9sZSI6IkFETUlOIiwiY29tcGFueSI6IjVlMmVkNDc3ZDlhOTQwNDkzNjU3NTZhNSIsImlhdCI6MTU4MDk4NDk0NSwiZXhwIjoxNTgxMDcxMzQ1fQ.W8ABPIBiU8LA_QmtE10LhIAWFxYizS7KHutHpgtxKyM",
								"type": "text"
							}
						],
						"url": {
							"raw": "{{host}}/blockchain/companies/5e3018646b4c56190ca6f26c/users",
							"host": [
								"{{host}}"
							],
							"path": [
								"blockchain",
								"companies",
								"5e3018646b4c56190ca6f26c",
								"users"
							]
						}
					},
					"response": []
				},
				{
					"name": "Get user permisions",
					"request": {
						"method": "GET",
						"header": [],
						"url": {
							"raw": "http://localhost:5000/blockchain/permissions/0x948dE04b43f94E6C01593a28CB65bcC29f09a749",
							"protocol": "http",
							"host": [
								"localhost"
							],
							"port": "5000",
							"path": [
								"blockchain",
								"permissions",
								"0x948dE04b43f94E6C01593a28CB65bcC29f09a749"
							]
						}
					},
					"response": []
				},
				{
					"name": "Create Company",
					"request": {
						"method": "POST",
						"header": [
							{
								"key": "Content-Type",
								"name": "Content-Type",
								"value": "application/json",
								"type": "text"
							}
						],
						"body": {
							"mode": "raw",
							"raw": "{\n\t\"company\": {\n\t\t\"_id\": \"5d5bc0f7d34a99362bbb2910\"\n\t},\n\t\n\t\"user\": {\n\t\t\"address\": \"0xa2B4A7Ba26FC883dD6c31e9Ef4b9b7b3c9D2B7F9\"\n\t}\n}"
						},
						"url": {
							"raw": "{{host}}/blockchain/companies",
							"host": [
								"{{host}}"
							],
							"path": [
								"blockchain",
								"companies"
							]
						}
					},
					"response": []
				}
			]
		},
		{
			"name": "Statistics",
			"item": [
				{
					"name": "Get Company Stat",
					"request": {
						"method": "GET",
						"header": [
							{
								"key": "X-Token-Jwt",
								"value": "eyJhbGciOiJIUzI1NiIsInR5cCI6IkpXVCJ9.eyJpZCI6IjVkNTVkM2QwY2QzMjBmMmI4MmNhM2NhOSIsImZpcnN0bmFtZSI6InJvbmRvIiwibGFzdG5hbWUiOiJtYW4iLCJyb2xlIjoiQURNSU4iLCJjb21wYW55IjoiNWQ1NWQ0MDljZDMyMGYyYjgyY2EzY2FhIiwiaWF0IjoxNTY4MTAwODM0LCJleHAiOjE1NjgxODcyMzR9.U0sVB4ZZlcoYjtrg6jUWaYOClCZ4VwYGmnOO2kUHEs0",
								"type": "text"
							}
						],
						"url": {
							"raw": "{{host}}/statistics/companies/5d55d409cd320f2b82ca3caa",
							"host": [
								"{{host}}"
							],
							"path": [
								"statistics",
								"companies",
								"5d55d409cd320f2b82ca3caa"
							]
						}
					},
					"response": []
				},
				{
					"name": "Get All",
					"request": {
						"method": "GET",
						"header": [
							{
								"key": "X-Token-Jwt",
								"type": "text",
								"value": "eyJhbGciOiJIUzI1NiIsInR5cCI6IkpXVCJ9.eyJpZCI6IjVkNTVkM2QwY2QzMjBmMmI4MmNhM2NhOSIsImZpcnN0bmFtZSI6InJvbmRvIiwibGFzdG5hbWUiOiJtYW4iLCJyb2xlIjoiQURNSU4iLCJjb21wYW55IjoiNWQ1NWQ0MDljZDMyMGYyYjgyY2EzY2FhIiwiaWF0IjoxNTY4MTAwODM0LCJleHAiOjE1NjgxODcyMzR9.U0sVB4ZZlcoYjtrg6jUWaYOClCZ4VwYGmnOO2kUHEs0"
							}
						],
						"url": {
							"raw": "{{host}}/statistics?companies&tests&certificates&transactions",
							"host": [
								"{{host}}"
							],
							"path": [
								"statistics"
							],
							"query": [
								{
									"key": "companies",
									"value": null
								},
								{
									"key": "tests",
									"value": null
								},
								{
									"key": "certificates",
									"value": null
								},
								{
									"key": "transactions",
									"value": null
								}
							]
						}
					},
					"response": []
				}
			]
		},
		{
			"name": "Transfers",
			"item": [
				{
					"name": "All",
					"request": {
						"method": "GET",
						"header": [
							{
								"key": "X-Token-Jwt",
								"type": "text",
								"value": "eyJhbGciOiJIUzI1NiIsInR5cCI6IkpXVCJ9.eyJpZCI6IjVkZjBiNTUxODU2NGQ0MzZkZDA0MWJkMyIsImZpcnN0bmFtZSI6Im1hbiIsImxhc3RuYW1lIjoicm9uZG8iLCJyb2xlIjoiQURNSU4iLCJjb21wYW55IjoiNWRmMGI1NTE4NTY0ZDQzNmRkMDQxYmQ0IiwiaWF0IjoxNTc2MDU2NDg5LCJleHAiOjE1NzYxNDI4ODl9.a97rBEVzVwcJ2R_LJcMcRQwTOcJq-iCl1SB-4pVmYLo"
							}
						],
						"url": {
							"raw": "{{host}}/transfers?companyId=5dd538cb48445a575b60c39c",
							"host": [
								"{{host}}"
							],
							"path": [
								"transfers"
							],
							"query": [
								{
									"key": "companyId",
									"value": "5dd538cb48445a575b60c39c"
								}
							]
						}
					},
					"response": []
				}
			],
			"protocolProfileBehavior": {}
		},
		{
			"name": "Instruments",
			"item": [
				{
					"name": "All",
					"request": {
						"method": "GET",
						"header": [
							{
								"key": "X-Token-Jwt",
								"value": " eyJhbGciOiJIUzI1NiIsInR5cCI6IkpXVCJ9.eyJpZCI6IjVlMzAxNDBkNmI0YzU2MTkwY2E2ZjI0ZSIsImZpcnN0bmFtZSI6ImF3ZGF3ZCIsImxhc3RuYW1lIjoiYXdkd2EiLCJyb2xlIjoiQURNSU4iLCJjb21wYW55IjoiNWUzMDE0MGQ2YjRjNTYxOTBjYTZmMjRmIiwiaWF0IjoxNTg0NzEwNDQyLCJleHAiOjE1ODU0MTA0NDJ9.RuP8ntpQZ7pLALXAoHuL7Wj3qxZwtYI1uZu47lsZcS4",
								"type": "text"
							}
						],
						"url": {
							"raw": "{{host}}/instruments",
							"host": [
								"{{host}}"
							],
							"path": [
								"instruments"
							]
						}
					},
					"response": []
				},
				{
					"name": "Create",
					"request": {
						"method": "POST",
						"header": [
							{
								"key": "X-Token-Jwt",
								"value": " eyJhbGciOiJIUzI1NiIsInR5cCI6IkpXVCJ9.eyJpZCI6IjVlMzAxNDBkNmI0YzU2MTkwY2E2ZjI0ZSIsImZpcnN0bmFtZSI6ImF3ZGF3ZCIsImxhc3RuYW1lIjoiYXdkd2EiLCJyb2xlIjoiQURNSU4iLCJjb21wYW55IjoiNWUzMDE0MGQ2YjRjNTYxOTBjYTZmMjRmIiwiaWF0IjoxNTg0NzEwNDQyLCJleHAiOjE1ODU0MTA0NDJ9.RuP8ntpQZ7pLALXAoHuL7Wj3qxZwtYI1uZu47lsZcS4",
								"type": "text"
							}
						],
						"body": {
							"mode": "raw",
							"raw": "{\n\t\"equipment\": \"TTTT\",\n\t\"trademark\": \"TTTT\",\n\t\"serialNumber\": \"TTTTT\",\n\t\"calibrationExpDate\": \"22-11-2020\",\n\t\"defaultForTests\": [\"chemical_composition\"]\n}",
							"options": {
								"raw": {
									"language": "json"
								}
							}
						},
						"url": {
							"raw": "{{host}}/instruments",
							"host": [
								"{{host}}"
							],
							"path": [
								"instruments"
							]
						}
					},
					"response": []
				},
				{
					"name": "Update",
					"request": {
						"method": "PUT",
						"header": [
							{
								"key": "X-Token-Jwt",
								"type": "text",
								"value": " eyJhbGciOiJIUzI1NiIsInR5cCI6IkpXVCJ9.eyJpZCI6IjVlMzAxNDBkNmI0YzU2MTkwY2E2ZjI0ZSIsImZpcnN0bmFtZSI6ImF3ZGF3ZCIsImxhc3RuYW1lIjoiYXdkd2EiLCJyb2xlIjoiQURNSU4iLCJjb21wYW55IjoiNWUzMDE0MGQ2YjRjNTYxOTBjYTZmMjRmIiwiaWF0IjoxNTg0NzEwNDQyLCJleHAiOjE1ODU0MTA0NDJ9.RuP8ntpQZ7pLALXAoHuL7Wj3qxZwtYI1uZu47lsZcS4"
							}
						],
						"body": {
							"mode": "raw",
							"raw": "{\n\t\"equipment\": \"433\",\n\t\"trademark\": \"TTTT\",\n\t\"serialNumber\": \"TTTTT\",\n\t\"calibrationExpDate\": \"2009-11-10T07:00:00+0000\",\n\t\"defaultForTests\": [\"chemical_composition\"]\n}",
							"options": {
								"raw": {
									"language": "json"
								}
							}
						},
						"url": {
							"raw": "{{host}}/instruments/5e777bf6e0df696f4514aacd",
							"host": [
								"{{host}}"
							],
							"path": [
								"instruments",
								"5e777bf6e0df696f4514aacd"
							]
						}
					},
					"response": []
				},
				{
					"name": "Remove All",
					"request": {
						"method": "DELETE",
						"header": [
							{
								"key": "X-Token-Jwt",
								"value": " eyJhbGciOiJIUzI1NiIsInR5cCI6IkpXVCJ9.eyJpZCI6IjVlMzAxNDBkNmI0YzU2MTkwY2E2ZjI0ZSIsImZpcnN0bmFtZSI6ImF3ZGF3ZCIsImxhc3RuYW1lIjoiYXdkd2EiLCJyb2xlIjoiQURNSU4iLCJjb21wYW55IjoiNWUzMDE0MGQ2YjRjNTYxOTBjYTZmMjRmIiwiaWF0IjoxNTg0NzEwNDQyLCJleHAiOjE1ODU0MTA0NDJ9.RuP8ntpQZ7pLALXAoHuL7Wj3qxZwtYI1uZu47lsZcS4",
								"type": "text"
							}
						],
						"url": {
							"raw": "{{host}}/instruments/bulk?ids[]=5e776d084923d35fb7fef34a",
							"host": [
								"{{host}}"
							],
							"path": [
								"instruments",
								"bulk"
							],
							"query": [
								{
									"key": "ids[]",
									"value": "5e776d084923d35fb7fef34a"
								}
							]
						}
					},
					"response": []
				}
			],
			"protocolProfileBehavior": {}
		},
		{
			"name": "Specifications",
			"item": [
				{
					"name": "All",
					"request": {
						"method": "GET",
						"header": [
							{
								"key": "X-Token-Jwt",
								"value": " eyJhbGciOiJIUzI1NiIsInR5cCI6IkpXVCJ9.eyJpZCI6IjVlODJjNjg3YjIzMWFiMDAzYmY2NDJlNCIsImZpcnN0bmFtZSI6IkthbGkiLCJsYXN0bmFtZSI6IldhbHNoIiwicm9sZSI6IkFETUlOIiwiY29tcGFueSI6IjVlODJjNjg3YjIzMWFiMDAzYmY2NDJlNSIsImlhdCI6MTU4Njk0NTA3OCwiZXhwIjoxNTg3NjQ1MDc4fQ.p5SYG2jDijgrEe6l0JMFoutb7e6HfbRHtluhPtMIbqs",
								"type": "text"
							}
						],
						"url": {
							"raw": "{{host}}/specifications",
							"host": [
								"{{host}}"
							],
							"path": [
								"specifications"
							]
						}
					},
					"response": []
				},
				{
					"name": "Create Bulk",
					"request": {
						"method": "POST",
						"header": [
							{
								"key": "X-Token-Jwt",
								"value": " eyJhbGciOiJIUzI1NiIsInR5cCI6IkpXVCJ9.eyJpZCI6IjVlODJjNjg3YjIzMWFiMDAzYmY2NDJlNCIsImZpcnN0bmFtZSI6IkthbGkiLCJsYXN0bmFtZSI6IldhbHNoIiwicm9sZSI6IkFETUlOIiwiY29tcGFueSI6IjVlODJjNjg3YjIzMWFiMDAzYmY2NDJlNSIsImlhdCI6MTU4Njk0NTA3OCwiZXhwIjoxNTg3NjQ1MDc4fQ.p5SYG2jDijgrEe6l0JMFoutb7e6HfbRHtluhPtMIbqs",
								"type": "text"
							}
						],
						"body": {
							"mode": "raw",
							"raw": "{\n\t\"name\": \"Vallourec1\",\n\t\"config\": [{\n\t\t\"entity\": \"certificate\",\n\t\t\"field\": \"certificateType\",\n\t\t\"value\": 3.2\n\t}]\n   \n}",
							"options": {
								"raw": {
									"language": "json"
								}
							}
						},
						"url": {
							"raw": "{{host}}/specifications/bulk",
							"host": [
								"{{host}}"
							],
							"path": [
								"specifications",
								"bulk"
							]
						}
					},
					"response": []
				},
				{
					"name": "Update",
					"request": {
						"method": "PUT",
						"header": [
							{
								"key": "X-Token-Jwt",
								"value": " eyJhbGciOiJIUzI1NiIsInR5cCI6IkpXVCJ9.eyJpZCI6IjVlODJjNjg3YjIzMWFiMDAzYmY2NDJlNCIsImZpcnN0bmFtZSI6IkthbGkiLCJsYXN0bmFtZSI6IldhbHNoIiwicm9sZSI6IkFETUlOIiwiY29tcGFueSI6IjVlODJjNjg3YjIzMWFiMDAzYmY2NDJlNSIsImlhdCI6MTU4Njk0NTA3OCwiZXhwIjoxNTg3NjQ1MDc4fQ.p5SYG2jDijgrEe6l0JMFoutb7e6HfbRHtluhPtMIbqs",
								"type": "text"
							}
						],
						"body": {
							"mode": "raw",
							"raw": "{\n\t\"name\": \"Vallourec2\",\n\t\"config\": [{\n\t\t\"entity\": \"certificate\",\n\t\t\"field\": \"certificateType\",\n\t\t\"value\": 3.1\n\t}]\n   \n}",
							"options": {
								"raw": {
									"language": "json"
								}
							}
						},
						"url": {
							"raw": "{{host}}/specifications/5e983f68e849a60280c84eae",
							"host": [
								"{{host}}"
							],
							"path": [
								"specifications",
								"5e983f68e849a60280c84eae"
							]
						}
					},
					"response": []
				},
				{
					"name": "Remove All",
					"request": {
						"method": "DELETE",
						"header": [
							{
								"key": "X-Token-Jwt",
								"value": " eyJhbGciOiJIUzI1NiIsInR5cCI6IkpXVCJ9.eyJpZCI6IjVlODJjNjg3YjIzMWFiMDAzYmY2NDJlNCIsImZpcnN0bmFtZSI6IkthbGkiLCJsYXN0bmFtZSI6IldhbHNoIiwicm9sZSI6IkFETUlOIiwiY29tcGFueSI6IjVlODJjNjg3YjIzMWFiMDAzYmY2NDJlNSIsImlhdCI6MTU4Njk0NTA3OCwiZXhwIjoxNTg3NjQ1MDc4fQ.p5SYG2jDijgrEe6l0JMFoutb7e6HfbRHtluhPtMIbqs",
								"type": "text"
							}
						],
						"url": {
							"raw": "{{host}}/specifications/bulk?ids[]=5e9894792a5ab802f53234a8",
							"host": [
								"{{host}}"
							],
							"path": [
								"specifications",
								"bulk"
							],
							"query": [
								{
									"key": "ids[]",
									"value": "5e9894792a5ab802f53234a8"
								}
							]
						}
					},
					"response": []
				}
			],
			"protocolProfileBehavior": {}
		},
		{
			"name": "Logs",
			"item": [
				{
					"name": "All",
					"request": {
						"method": "GET",
						"header": [
							{
								"key": "X-Token-Jwt",
								"value": " eyJhbGciOiJIUzI1NiIsInR5cCI6IkpXVCJ9.eyJpZCI6IjVlODJjNjg3YjIzMWFiMDAzYmY2NDJkZCIsImZpcnN0bmFtZSI6Ik5lbGxhIiwibGFzdG5hbWUiOiJMaXR0bGUiLCJyb2xlIjoiU1VQRVJfQURNSU4iLCJjb21wYW55IjoiNWU4MmM2ODdiMjMxYWIwMDNiZjY0MmRlIiwiaWF0IjoxNTg1ODE4NDQ2LCJleHAiOjE1ODY1MTg0NDZ9.MPjM8uosg-q9hdVWfYOQ9XPkoU8RkGPAh3J8Eyp8tPk",
								"type": "text"
							}
						],
						"url": {
							"raw": "{{host}}/logs?userId=5e82c687b231ab003bf642e4",
							"host": [
								"{{host}}"
							],
							"path": [
								"logs"
							],
							"query": [
								{
									"key": "userId",
									"value": "5e82c687b231ab003bf642e4"
								}
							]
						}
					},
					"response": []
				},
				{
					"name": "Remove All",
					"request": {
						"method": "DELETE",
						"header": [
							{
								"key": "X-Token-Jwt",
								"value": " eyJhbGciOiJIUzI1NiIsInR5cCI6IkpXVCJ9.eyJpZCI6IjVlMzAxNDBkNmI0YzU2MTkwY2E2ZjI0ZSIsImZpcnN0bmFtZSI6ImF3ZGF3ZCIsImxhc3RuYW1lIjoiYXdkd2EiLCJyb2xlIjoiQURNSU4iLCJjb21wYW55IjoiNWUzMDE0MGQ2YjRjNTYxOTBjYTZmMjRmIiwiaWF0IjoxNTg0NzEwNDQyLCJleHAiOjE1ODU0MTA0NDJ9.RuP8ntpQZ7pLALXAoHuL7Wj3qxZwtYI1uZu47lsZcS4",
								"type": "text"
							}
						],
						"url": {
							"raw": "{{host}}/instruments/bulk?ids[]=5e776d084923d35fb7fef34a",
							"host": [
								"{{host}}"
							],
							"path": [
								"instruments",
								"bulk"
							],
							"query": [
								{
									"key": "ids[]",
									"value": "5e776d084923d35fb7fef34a"
								}
							]
						}
					},
					"response": []
				}
			],
			"protocolProfileBehavior": {}
		},
		{
			"name": "Archive",
			"item": [
				{
					"name": "All certificates",
					"request": {
						"method": "GET",
						"header": [
							{
								"key": "X-Token-Jwt",
								"value": " eyJhbGciOiJIUzI1NiIsInR5cCI6IkpXVCJ9.eyJpZCI6IjVlMmVkNDc3ZDlhOTQwNDkzNjU3NTZhNCIsImZpcnN0bmFtZSI6ImR3dyIsImxhc3RuYW1lIjoiYXdkIiwicm9sZSI6IkFETUlOIiwiY29tcGFueSI6IjVlMmVkNDc3ZDlhOTQwNDkzNjU3NTZhNSIsImlhdCI6MTU4NTA1Nzk3OCwiZXhwIjoxNTg1NzU3OTc4fQ.iq2ZnUUBEFmYZiPwpmh_laSyLfVyeMmOTGTJiEevcLQ",
								"type": "text"
							}
						],
						"url": {
							"raw": "{{host}}/archive/certificates",
							"host": [
								"{{host}}"
							],
							"path": [
								"archive",
								"certificates"
							]
						}
					},
					"response": []
				},
				{
					"name": "Get certificate",
					"request": {
						"method": "GET",
						"header": [
							{
								"key": "X-Token-Jwt",
								"value": " eyJhbGciOiJIUzI1NiIsInR5cCI6IkpXVCJ9.eyJpZCI6IjVlMmVkNDc3ZDlhOTQwNDkzNjU3NTZhNCIsImZpcnN0bmFtZSI6ImR3dyIsImxhc3RuYW1lIjoiYXdkIiwicm9sZSI6IkFETUlOIiwiY29tcGFueSI6IjVlMmVkNDc3ZDlhOTQwNDkzNjU3NTZhNSIsImlhdCI6MTU4NTA1Nzk3OCwiZXhwIjoxNTg1NzU3OTc4fQ.iq2ZnUUBEFmYZiPwpmh_laSyLfVyeMmOTGTJiEevcLQ",
								"type": "text"
							}
						],
						"url": {
							"raw": "{{host}}/archive/certificates/5e7b4a0743497411f5a50027",
							"host": [
								"{{host}}"
							],
							"path": [
								"archive",
								"certificates",
								"5e7b4a0743497411f5a50027"
							]
						}
					},
					"response": []
				},
				{
					"name": "Remove certificates",
					"request": {
						"method": "DELETE",
						"header": [
							{
								"key": "X-Token-Jwt",
								"value": " eyJhbGciOiJIUzI1NiIsInR5cCI6IkpXVCJ9.eyJpZCI6IjVlMmVkNDc3ZDlhOTQwNDkzNjU3NTZhNCIsImZpcnN0bmFtZSI6ImR3dyIsImxhc3RuYW1lIjoiYXdkIiwicm9sZSI6IkFETUlOIiwiY29tcGFueSI6IjVlMmVkNDc3ZDlhOTQwNDkzNjU3NTZhNSIsImlhdCI6MTU4NTA1Nzk3OCwiZXhwIjoxNTg1NzU3OTc4fQ.iq2ZnUUBEFmYZiPwpmh_laSyLfVyeMmOTGTJiEevcLQ",
								"type": "text"
							}
						],
						"url": {
							"raw": "{{host}}/archive/certificates/bulk?ids[]=5e7b4a0743497411f5a50026",
							"host": [
								"{{host}}"
							],
							"path": [
								"archive",
								"certificates",
								"bulk"
							],
							"query": [
								{
									"key": "ids[]",
									"value": "5e7b4a0743497411f5a50026"
								}
							]
						}
					},
					"response": []
				}
			],
			"protocolProfileBehavior": {}
		},
		{
			"name": "Clean",
			"request": {
				"method": "POST",
				"header": [
					{
						"key": "Content-Type",
						"name": "Content-Type",
						"value": "application/json",
						"type": "text"
					}
				],
				"body": {
					"mode": "raw",
					"raw": "{\n\t\"collections\": [\"companies\"]\n}"
				},
				"url": {
					"raw": "{{host}}/clean",
					"host": [
						"{{host}}"
					],
					"path": [
						"clean"
					]
				}
			},
			"response": []
		},
		{
			"name": "CLEAR ES",
			"request": {
				"method": "DELETE",
				"header": [],
				"url": {
					"raw": "http://localhost:9200/certificates",
					"protocol": "http",
					"host": [
						"localhost"
					],
					"port": "9200",
					"path": [
						"certificates"
					]
				}
			},
			"response": []
		},
		{
			"name": "Get from elastic",
			"request": {
				"method": "GET",
				"header": [],
				"url": {
					"raw": "http://localhost:9200/transfers/_search?size=200&pretty=true&q=*:*",
					"protocol": "http",
					"host": [
						"localhost"
					],
					"port": "9200",
					"path": [
						"transfers",
						"_search"
					],
					"query": [
						{
							"key": "size",
							"value": "200"
						},
						{
							"key": "pretty",
							"value": "true"
						},
						{
							"key": "q",
							"value": "*:*"
						}
					]
				}
			},
			"response": []
		},
		{
			"name": "Get mapping from elastic",
			"request": {
				"method": "GET",
				"header": [],
				"url": {
					"raw": "http://localhost:9200/certificates/_mapping",
					"protocol": "http",
					"host": [
						"localhost"
					],
					"port": "9200",
					"path": [
						"certificates",
						"_mapping"
					]
				}
			},
			"response": []
		},
		{
			"name": "Update mapping",
			"request": {
				"method": "PUT",
				"header": [
					{
						"key": "Content-Type",
						"name": "Content-Type",
						"value": "application/json",
						"type": "text"
					}
				],
				"body": {
					"mode": "raw",
					"raw": "{\n  \"properties\": {\n    \"orderNumber\": {\n      \"type\": \"keyword\"\n    }\n  }\n}",
					"options": {
						"raw": {
							"language": "json"
						}
					}
				},
				"url": {
					"raw": "http://localhost:9200/transfers/_mappings",
					"protocol": "http",
					"host": [
						"localhost"
					],
					"port": "9200",
					"path": [
						"transfers",
						"_mappings"
					]
				}
			},
			"response": []
		},
		{
			"name": "Create index",
			"protocolProfileBehavior": {
				"disableBodyPruning": true
			},
			"request": {
				"method": "GET",
				"header": [
					{
						"key": "Content-Type",
						"name": "Content-Type",
						"type": "text",
						"value": "application/json"
					}
				],
				"body": {
					"mode": "raw",
					"raw": "",
					"options": {
						"raw": {
							"language": "json"
						}
					}
				},
				"url": {
					"raw": "http://localhost:5000/",
					"protocol": "http",
					"host": [
						"localhost"
					],
					"port": "5000",
					"path": [
						""
					]
				}
			},
			"response": []
		}
	]
}